breadcrumbs/__init__.py
breadcrumbs/breadcrumbs.py
breadcrumbs/middleware.py
breadcrumbs/models.py
breadcrumbs/urls.py
breadcrumbs/utils.py
breadcrumbs/views.py
breadcrumbs/tests/__init__.py
breadcrumbs/tests/breadcrumbs_tests.py
breadcrumbs/tests/flatpages_tests.py
breadcrumbs/tests/singleton_tests.py
breadcrumbs/tests/urls.py
breadcrumbs/tests/views.py
django_breadcrumbs-1.1.4a1.dist-info/DESCRIPTION.rst
django_breadcrumbs-1.1.4a1.dist-info/METADATA
django_breadcrumbs-1.1.4a1.dist-info/RECORD
django_breadcrumbs-1.1.4a1.dist-info/WHEEL
django_breadcrumbs-1.1.4a1.dist-info/metadata.json
django_breadcrumbs-1.1.4a1.dist-info/top_level.txt
