Metadata-Version: 2.0
Name: django-breadcrumbs
Version: 1.1.4a1
Summary: Easy to use generic breadcrumbs system for Django framework.
Home-page: http://github.com/chronossc/django-breadcrumbs
Author: Felipe 'chronos' Prenholato
Author-email: philipe.rp@gmail.com
License: NEW BSD LICENSE: http://www.opensource.org/licenses/bsd-license.php
Platform: UNKNOWN
Classifier: Development Status :: 5 - Production/Stable
Classifier: Environment :: Web Environment
Classifier: Framework :: Django
Classifier: Intended Audience :: Developers
Classifier: License :: OSI Approved :: BSD License
Classifier: Operating System :: OS Independent
Classifier: Programming Language :: Python
Requires-Dist: Django (>=1.3.4)
Requires-Dist: six
